scripts/__init__.py
scripts/describe.py
scripts/dispatcher.py
scripts/exporter.py
scripts/kill.py
scripts/lock.py
scripts/ls.py
scripts/node_cleanup.py
scripts/openstack.py
scripts/prune_logs.py
scripts/queue.py
scripts/reimage.py
scripts/report.py
scripts/results.py
scripts/run.py
scripts/schedule.py
scripts/suite.py
scripts/supervisor.py
scripts/update_inventory.py
scripts/updatekeys.py
scripts/wait.py
teuthology/__init__.py
teuthology/beanstalk.py
teuthology/config.py
teuthology/contextutil.py
teuthology/describe_tests.py
teuthology/exceptions.py
teuthology/exit.py
teuthology/exporter.py
teuthology/job_status.py
teuthology/kill.py
teuthology/ls.py
teuthology/misc.py
teuthology/packaging.py
teuthology/parallel.py
teuthology/prune.py
teuthology/reimage.py
teuthology/repo_utils.py
teuthology/report.py
teuthology/results.py
teuthology/run.py
teuthology/run_tasks.py
teuthology/safepath.py
teuthology/schedule.py
teuthology/scrape.py
teuthology/timer.py
teuthology/dispatcher/__init__.py
teuthology/dispatcher/supervisor.py
teuthology/lock/__init__.py
teuthology/lock/cli.py
teuthology/lock/ops.py
teuthology/lock/query.py
teuthology/lock/util.py
teuthology/nuke/__init__.py
teuthology/openstack/__init__.py
teuthology/openstack/archive-key
teuthology/openstack/archive-key.pub
teuthology/openstack/openstack-centos-6.5-user-data.txt
teuthology/openstack/openstack-centos-7.0-user-data.txt
teuthology/openstack/openstack-centos-7.1-user-data.txt
teuthology/openstack/openstack-centos-7.2-user-data.txt
teuthology/openstack/openstack-debian-8.0-user-data.txt
teuthology/openstack/openstack-opensuse-42.1-user-data.txt
teuthology/openstack/openstack-teuthology.cron
teuthology/openstack/openstack-teuthology.init
teuthology/openstack/openstack-ubuntu-12.04-user-data.txt
teuthology/openstack/openstack-ubuntu-14.04-user-data.txt
teuthology/openstack/openstack-user-data.txt
teuthology/openstack/setup-openstack.sh
teuthology/orchestra/__init__.py
teuthology/orchestra/cluster.py
teuthology-1.2.2.dist-info/licenses/LICENSE
teuthology-1.2.2.dist-info/METADATA
teuthology-1.2.2.dist-info/WHEEL
teuthology-1.2.2.dist-info/entry_points.txt
teuthology-1.2.2.dist-info/top_level.txt
teuthology-1.2.2.dist-info/RECORD
